sshremote
