Metadata-Version: 2.1
Name: sshremote
Version: 0.0.9
Summary: sshremote
Home-page: https://github.com/u1234x1234/sshremote
Author: u1234x1234
Author-email: u1234x1234@gmail.com
License: MIT
Platform: UNKNOWN
Classifier: Programming Language :: Python :: 3
Classifier: Development Status :: 3 - Alpha
Classifier: Topic :: Utilities
Classifier: License :: OSI Approved :: MIT License
